Metadata-Version: 2.1
Name: wait-for-me
Version: 0.0.1
Summary: 调用此方法可打印9*9乘法表
Home-page: https://github.com/mxq360360/suibian
Author: Bruce
Author-email: hf15603950816@163.com
License: UNKNOWN
Platform: UNKNOWN
Classifier: Programming Language :: Python :: 3
Classifier: License :: OSI Approved :: MIT License
Classifier: Operating System :: OS Independent
Requires-Python: >=3.7
